gui_engine/__init__.py
gui_engine/main.py
gui_engine-0.1.dist-info/METADATA
gui_engine-0.1.dist-info/WHEEL
gui_engine-0.1.dist-info/top_level.txt
gui_engine-0.1.dist-info/RECORD
